plantstar_shared/DataCollectionModuleConstants.py
plantstar_shared/DataCollectionModuleProcessNames.py
plantstar_shared/HmiConstants.py
plantstar_shared/HuskyInterfacePacketTypes.py
plantstar_shared/MockRawDataProcessor.py
plantstar_shared/RawDataProcessorInterfaceActions.py
plantstar_shared/SysconType.py
plantstar_shared/__init__.py
plantstar_shared/add_size_onto_string_and_return.py
plantstar_shared/api_types.py
plantstar_shared/convert_bytes_to_object.py
plantstar_shared/convert_object_to_bytes.py
plantstar_shared/errors.py
plantstar_shared/global_definitions.py
plantstar_shared/is_valid_signed_string.py
plantstar_shared/obtain_raw_data_processor_function_for_action_name.py
plantstar_shared/syscon_image_field.py
plantstar_shared/syscon_json.py
plantstar_shared/tcp_socket_utils.py
plantstar_shared-2.0.3.0.2.36.dist-info/METADATA
plantstar_shared-2.0.3.0.2.36.dist-info/WHEEL
plantstar_shared-2.0.3.0.2.36.dist-info/top_level.txt
plantstar_shared-2.0.3.0.2.36.dist-info/RECORD
