Metadata-Version: 2.4
Name: plantstar-shared
Version: 2.0.3.0.2.36
Summary: Shared code used in plantstar_apu and plantstar_dcm
Home-page: https://github.com/SYSCON-International/plantstar_shared
Author: SYSCON International
Author-email: dev@syscon-intl.com
Classifier: Programming Language :: Python :: 3
Classifier: License :: OSI Approved :: MIT License
Classifier: Operating System :: OS Independent
Requires-Dist: Django>=4.2.0
Requires-Dist: msgpack>=1.0.4
Requires-Dist: psycopg2>=2.9.9
Requires-Dist: python-dateutil>=2.8.2
Requires-Dist: pytz>=2023.4
Requires-Dist: requests>=2.31.0
Dynamic: author
Dynamic: author-email
Dynamic: classifier
Dynamic: description
Dynamic: description-content-type
Dynamic: home-page
Dynamic: requires-dist
Dynamic: summary
